vgs_cli-0.1.1.data/scripts/vgs
vgscli/__init__.py
vgscli/_version.py
vgscli/api.py
vgscli/auth.py
vgscli/config.py
vgscli/routes.py
vgscli/utils.py
vgs_cli-0.1.1.dist-info/LICENSE
vgs_cli-0.1.1.dist-info/METADATA
vgs_cli-0.1.1.dist-info/WHEEL
vgs_cli-0.1.1.dist-info/top_level.txt
vgs_cli-0.1.1.dist-info/RECORD
