Metadata-Version: 2.1
Name: vgs-cli
Version: 0.1.1
Summary: VGS Client
Home-page: https://github.com/verygoodsecurity/vgs-cli
Author: Very Good Security
Author-email: dev@verygoodsecurity.com
License: BSD
Platform: any
Classifier: Intended Audience :: Developers
Classifier: License :: OSI Approved :: BSD License
Classifier: Operating System :: OS Independent
Classifier: Programming Language :: Python
Classifier: Topic :: Software Development :: Libraries :: Python Modules
Requires-Dist: pyaml (==17.12.1)
Requires-Dist: PyYAML (==3.13)
Requires-Dist: simple-rest-client (==0.5.2)
Requires-Dist: requests (==2.18.4)
Requires-Dist: PyJWT (==1.5.3)
Provides-Extra: tests
Requires-Dist: pytest (==3.10.0); extra == 'tests'
Requires-Dist: pytest-html (==1.19.0); extra == 'tests'
Requires-Dist: pytest-mock (==1.10.0); extra == 'tests'
Requires-Dist: requests-mock (==1.5.2); extra == 'tests'
